example/__init__.py
example/__main__.py
example/demo.py
fp_github_template_example-0.0.3.dist-info/LICENSE
fp_github_template_example-0.0.3.dist-info/METADATA
fp_github_template_example-0.0.3.dist-info/WHEEL
fp_github_template_example-0.0.3.dist-info/entry_points.txt
fp_github_template_example-0.0.3.dist-info/top_level.txt
fp_github_template_example-0.0.3.dist-info/RECORD
