Metadata-Version: 2.1
Name: fp-github-template-example
Version: 0.0.3
Summary: package example
Author-email: Filipe Pina <shelf-corncob-said@duck.com>
Project-URL: Homepage, https://github.com/fopina/python-package-template
Requires-Python: >=3.10
License-File: LICENSE
